{"jsonrpc":"2.0","id":0,"result":{"qPropEntry":{"qProperty":{"qInfo":{"qId":"b6965b22-2ca4-45fa-b8c4-dfbda8485ff4","qType":"sheet"},"qMetaDef":{"title":"Sheet Usage","description":""},"rank":0.39404296875,"thumbnail":{"qStaticContentUrlDef":{"qUrl":"/appcontent/58787822-1c29-45f8-a366-1305f95251ef/Icon_Data_Storytelling_grey.png"}},"columns":36,"rows":18,"cells":[{"name":"KuTfDZ","type":"filterpane","col":0,"row":0,"colspan":36,"rowspan":1,"bounds":{"y":0,"x":0,"width":100,"height":5.555555555555555}},{"name":"XWALt","type":"table","col":9,"row":9,"colspan":27,"rowspan":9,"bounds":{"y":50,"x":25,"width":75,"height":50}},{"name":"tDqdKeP","type":"table","col":9,"row":1,"colspan":27,"rowspan":8,"bounds":{"y":5.555555555555555,"x":25,"width":75,"height":44.44444444444444}},{"name":"UCgsfS","type":"barchart","col":0,"row":1,"colspan":9,"rowspan":17,"bounds":{"y":5.555555555555555,"x":0,"width":25,"height":94.44444444444444}}],"qChildListDef":{"qData":{"title":"/title"}},"gridResolution":"large"},"qChildren":[{"qProperty":{"qInfo":{"qId":"KuTfDZ","qType":"filterpane"},"qMetaDef":{},"qChildListDef":{"qData":{"info":"/qInfo"}},"showTitles":false,"title":"","subtitle":"","footnote":"","showDetails":true,"visualization":"filterpane"},"qChildren":[{"qProperty":{"qInfo":{"qId":"3238f901-c002-455e-b277-e17e6046d275","qType":"listbox"},"qMetaDef":{},"qListObjectDef":{"qLibraryId":"fkvNe","qDef":{"qGrouping":"N","qFieldDefs":[],"qFieldLabels":[],"qSortCriterias":[{"qSortByState":1,"qSortByNumeric":1,"qSortByLoadOrder":1,"qExpression":{}}],"qNumberPresentations":[],"qActiveField":0,"autoSort":false,"cId":"uLKuEv"},"qFrequencyMode":"N","qShowAlternatives":true,"qInitialDataFetch":[],"qExpressions":[],"qOtherTotalSpec":{}},"showTitles":true,"title":"Latest Activity Measure","subtitle":"","footnote":"","showDetails":false,"visualization":"listbox"},"qChildren":[]},{"qProperty":{"qInfo":{"qId":"pqNaLq","qType":"listbox"},"qMetaDef":{},"qListObjectDef":{"qLibraryId":"DXqMQM","qDef":{"qGrouping":"N","qFieldDefs":[],"qFieldLabels":[],"qSortCriterias":[{"qSortByState":1,"qSortByNumeric":1,"qSortByAscii":1,"qSortByLoadOrder":1,"qExpression":{}}],"qNumberPresentations":[],"qActiveField":0,"autoSort":true},"qFrequencyMode":"N","qShowAlternatives":true,"qInitialDataFetch":[],"qExpressions":[]},"title":"App","visualization":"listbox"},"qChildren":[]},{"qProperty":{"qInfo":{"qId":"da963d5e-4048-4062-a29d-c7232750e52c","qType":"listbox"},"qMetaDef":{},"qListObjectDef":{"qDef":{"qGrouping":"N","qFieldDefs":["App Stream (Active Apps)"],"qFieldLabels":["App Stream (Active Apps)"],"qSortCriterias":[{"qSortByState":1,"qSortByNumeric":1,"qSortByAscii":1,"qSortByLoadOrder":1,"qExpression":{}}],"qNumberPresentations":[],"qActiveField":0,"autoSort":true,"cId":"scUWe"},"qFrequencyMode":"N","qShowAlternatives":true,"qInitialDataFetch":[],"qExpressions":[],"qOtherTotalSpec":{}},"showTitles":true,"title":"App Stream","subtitle":"","footnote":"","showDetails":false,"visualization":"listbox"},"qChildren":[]},{"qProperty":{"qInfo":{"qId":"c950f702-c94f-4f4f-96c2-524429a625c4","qType":"listbox"},"qMetaDef":{},"qListObjectDef":{"qLibraryId":"bKvjJfM","qDef":{"qGrouping":"N","qFieldDefs":[],"qFieldLabels":[],"qSortCriterias":[{"qSortByState":1,"qSortByNumeric":1,"qSortByAscii":1,"qSortByLoadOrder":1,"qExpression":{}}],"qNumberPresentations":[],"qActiveField":0,"autoSort":true,"cId":"VExUtH"},"qFrequencyMode":"N","qShowAlternatives":true,"qInitialDataFetch":[],"qExpressions":[],"qOtherTotalSpec":{}},"showTitles":true,"title":"Sheet Name","subtitle":"","footnote":"","showDetails":false,"visualization":"listbox"},"qChildren":[]},{"qProperty":{"qInfo":{"qId":"95241f29-2edf-447f-bf2e-e8d46d2a4d8f","qType":"listbox"},"qMetaDef":{},"qListObjectDef":{"qLibraryId":"ed79d6fa-44e1-4edb-a43e-831096106fc8","qDef":{"qGrouping":"N","qFieldDefs":[],"qFieldLabels":[],"qSortCriterias":[{"qSortByState":1,"qSortByNumeric":1,"qSortByAscii":1,"qSortByLoadOrder":1,"qExpression":{}}],"qNumberPresentations":[],"qActiveField":0,"autoSort":true,"cId":"PRGTxN"},"qFrequencyMode":"N","qShowAlternatives":true,"qInitialDataFetch":[],"qExpressions":[],"qOtherTotalSpec":{}},"showTitles":true,"title":"Sheet Type","subtitle":"","footnote":"","showDetails":false,"visualization":"listbox"},"qChildren":[]},{"qProperty":{"qInfo":{"qId":"16eb3c68-88c3-4ecd-8db2-540b6a7419ee","qType":"listbox"},"qMetaDef":{},"qListObjectDef":{"qDef":{"qGrouping":"N","qFieldDefs":["Sheet Created or Used Timeframe"],"qFieldLabels":[""],"qSortCriterias":[{"qSortByState":1,"qSortByNumeric":1,"qSortByLoadOrder":1,"qExpression":{}}],"qNumberPresentations":[],"qActiveField":0,"autoSort":false,"cId":"sSpmZa"},"qFrequencyMode":"N","qShowAlternatives":true,"qInitialDataFetch":[],"qExpressions":[],"qOtherTotalSpec":{}},"showTitles":true,"title":"Sheet Created or Used Timeframe","subtitle":"","footnote":"","showDetails":false,"visualization":"listbox"},"qChildren":[]},{"qProperty":{"qInfo":{"qId":"d46c0898-f3af-4bc1-a00f-c178329b63e0","qType":"listbox"},"qMetaDef":{},"qListObjectDef":{"qLibraryId":"hcEGnA","qDef":{"qGrouping":"N","qFieldDefs":[],"qFieldLabels":[],"qSortCriterias":[{"qSortByState":1,"qSortByNumeric":1,"qSortByAscii":1,"qSortByLoadOrder":1,"qExpression":{}}],"qNumberPresentations":[],"qActiveField":0,"autoSort":true,"cId":"WLVEqe"},"qFrequencyMode":"N","qShowAlternatives":true,"qInitialDataFetch":[],"qExpressions":[],"qOtherTotalSpec":{}},"showTitles":true,"title":"App Owner","subtitle":"","footnote":"","showDetails":false,"visualization":"listbox"},"qChildren":[]},{"qProperty":{"qInfo":{"qId":"a5150c2d-705b-4a00-a865-e47f975e6a11","qType":"listbox"},"qMetaDef":{},"qListObjectDef":{"qLibraryId":"aHTED","qDef":{"qGrouping":"N","qFieldDefs":[],"qFieldLabels":[],"qSortCriterias":[{"qSortByState":1,"qSortByNumeric":1,"qSortByAscii":1,"qSortByLoadOrder":1,"qExpression":{}}],"qNumberPresentations":[],"qActiveField":0,"autoSort":true,"cId":"FqtFQt"},"qFrequencyMode":"N","qShowAlternatives":true,"qInitialDataFetch":[],"qExpressions":[],"qOtherTotalSpec":{}},"showTitles":true,"title":"App Object Owner","subtitle":"","footnote":"","showDetails":false,"visualization":"listbox"},"qChildren":[]}]},{"qProperty":{"qInfo":{"qId":"XWALt","qType":"table"},"qMetaDef":{},"qHyperCubeDef":{"qDimensions":[{"qLibraryId":"DXqMQM","qDef":{"qGrouping":"N","qFieldDefs":[],"qFieldLabels":[],"qSortCriterias":[{"qSortByNumeric":1,"qSortByAscii":1,"qSortByLoadOrder":1,"qExpression":{}}],"qNumberPresentations":[],"qActiveField":0,"autoSort":true,"cId":"WjfdhJ","othersLabel":"Others","textAlign":{"auto":true,"align":"left"},"representation":{"type":"text","urlLabel":""}},"qNullSuppression":true,"qOtherTotalSpec":{"qOtherMode":"OTHER_OFF","qOtherCounted":{"qv":"10"},"qOtherLimit":{"qv":"0"},"qOtherLimitMode":"OTHER_GE_LIMIT","qForceBadValueKeeping":true,"qApplyEvenWhenPossiblyWrongResult":true,"qOtherSortMode":"OTHER_SORT_DESCENDING","qTotalMode":"TOTAL_OFF","qReferencedExpression":{}},"qOtherLabel":{"qv":"Others"},"qTotalLabel":{},"qCalcCond":{},"qAttributeExpressions":[],"qAttributeDimensions":[],"qCalcCondition":{"qCond":{},"qMsg":{}}},{"qLibraryId":"pwkJgCV","qDef":{"qGrouping":"N","qFieldDefs":[],"qFieldLabels":[],"qSortCriterias":[{"qSortByNumeric":1,"qSortByAscii":1,"qSortByLoadOrder":1,"qExpression":{}}],"qNumberPresentations":[],"qActiveField":0,"autoSort":true,"cId":"PmtmhKJ","othersLabel":"Others","textAlign":{"auto":true,"align":"left"},"representation":{"type":"text","urlLabel":""}},"qOtherTotalSpec":{"qOtherMode":"OTHER_OFF","qOtherCounted":{"qv":"10"},"qOtherLimit":{"qv":"0"},"qOtherLimitMode":"OTHER_GE_LIMIT","qForceBadValueKeeping":true,"qApplyEvenWhenPossiblyWrongResult":true,"qOtherSortMode":"OTHER_SORT_DESCENDING","qTotalMode":"TOTAL_OFF","qReferencedExpression":{}},"qOtherLabel":{"qv":"Others"},"qTotalLabel":{},"qCalcCond":{},"qAttributeExpressions":[],"qAttributeDimensions":[],"qCalcCondition":{"qCond":{},"qMsg":{}}},{"qLibraryId":"bKvjJfM","qDef":{"qGrouping":"N","qFieldDefs":[],"qFieldLabels":[],"qSortCriterias":[{"qSortByNumeric":1,"qSortByAscii":1,"qSortByLoadOrder":1,"qExpression":{}}],"qNumberPresentations":[],"qActiveField":0,"autoSort":true,"cId":"TqCyjx","othersLabel":"Others","textAlign":{"auto":true,"align":"left"},"representation":{"type":"text","urlLabel":""}},"qNullSuppression":true,"qOtherTotalSpec":{"qOtherMode":"OTHER_OFF","qOtherCounted":{"qv":"10"},"qOtherLimit":{"qv":"0"},"qOtherLimitMode":"OTHER_GE_LIMIT","qForceBadValueKeeping":true,"qApplyEvenWhenPossiblyWrongResult":true,"qOtherSortMode":"OTHER_SORT_DESCENDING","qTotalMode":"TOTAL_OFF","qReferencedExpression":{}},"qOtherLabel":{"qv":"Others"},"qTotalLabel":{},"qCalcCond":{},"qAttributeExpressions":[],"qAttributeDimensions":[],"qCalcCondition":{"qCond":{},"qMsg":{}}},{"qLibraryId":"ed79d6fa-44e1-4edb-a43e-831096106fc8","qDef":{"qGrouping":"N","qFieldDefs":[],"qFieldLabels":[],"qSortCriterias":[{"qSortByNumeric":1,"qSortByAscii":1,"qSortByLoadOrder":1,"qExpression":{}}],"qNumberPresentations":[],"qActiveField":0,"autoSort":true,"cId":"WjmfDRX","othersLabel":"Others","textAlign":{"auto":true,"align":"left"},"representation":{"type":"text","urlLabel":""}},"qOtherTotalSpec":{"qOtherMode":"OTHER_OFF","qOtherCounted":{"qv":"10"},"qOtherLimit":{"qv":"0"},"qOtherLimitMode":"OTHER_GE_LIMIT","qForceBadValueKeeping":true,"qApplyEvenWhenPossiblyWrongResult":true,"qOtherSortMode":"OTHER_SORT_DESCENDING","qTotalMode":"TOTAL_OFF","qReferencedExpression":{}},"qOtherLabel":{"qv":"Others"},"qTotalLabel":{},"qCalcCond":{},"qAttributeExpressions":[],"qAttributeDimensions":[],"qCalcCondition":{"qCond":{},"qMsg":{}}},{"qDef":{"qGrouping":"N","qFieldDefs":["App Object Created Date"],"qFieldLabels":["Created"],"qSortCriterias":[{"qSortByNumeric":-1,"qSortByAscii":1,"qSortByLoadOrder":1,"qExpression":{}}],"qNumberPresentations":[],"qActiveField":0,"autoSort":false,"cId":"MVuJDGk","othersLabel":"Others","textAlign":{"auto":true,"align":"left"},"representation":{"type":"text","urlLabel":""}},"qOtherTotalSpec":{"qOtherMode":"OTHER_OFF","qOtherCounted":{"qv":"10"},"qOtherLimit":{"qv":"0"},"qOtherLimitMode":"OTHER_GE_LIMIT","qForceBadValueKeeping":true,"qApplyEvenWhenPossiblyWrongResult":true,"qOtherSortMode":"OTHER_SORT_DESCENDING","qTotalMode":"TOTAL_OFF","qReferencedExpression":{}},"qOtherLabel":{"qv":"Others"},"qTotalLabel":{},"qCalcCond":{},"qAttributeExpressions":[],"qAttributeDimensions":[],"qCalcCondition":{"qCond":{},"qMsg":{}}},{"qDef":{"qGrouping":"N","qFieldDefs":["Sheet Created or Used Timeframe"],"qFieldLabels":["Latest Activity Range"],"qSortCriterias":[{"qSortByNumeric":1,"qSortByAscii":1,"qSortByLoadOrder":1,"qExpression":{}}],"qNumberPresentations":[],"qActiveField":0,"autoSort":true,"cId":"nFHpwLD","othersLabel":"Others","textAlign":{"auto":true,"align":"left"},"representation":{"type":"text","urlLabel":""}},"qOtherTotalSpec":{"qOtherMode":"OTHER_OFF","qOtherCounted":{"qv":"10"},"qOtherLimit":{"qv":"0"},"qOtherLimitMode":"OTHER_GE_LIMIT","qForceBadValueKeeping":true,"qApplyEvenWhenPossiblyWrongResult":true,"qOtherSortMode":"OTHER_SORT_DESCENDING","qTotalMode":"TOTAL_OFF","qReferencedExpression":{}},"qOtherLabel":{"qv":"Others"},"qTotalLabel":{},"qCalcCond":{},"qAttributeExpressions":[{"qExpression":"$(c_red_alpha([Sheet Created or Used Timeframe]))","qAttribute":true,"id":"cellBackgroundColor"}],"qAttributeDimensions":[],"qCalcCondition":{"qCond":{},"qMsg":{}}},{"qLibraryId":"KHpnpbn","qDef":{"qGrouping":"N","qFieldDefs":[],"qFieldLabels":[],"qSortCriterias":[{"qSortByNumeric":1,"qSortByAscii":1,"qSortByLoadOrder":1,"qExpression":{}}],"qNumberPresentations":[],"qActiveField":0,"autoSort":true,"cId":"TPPuG","othersLabel":"Others","textAlign":{"auto":true,"align":"left"},"representation":{"type":"text","urlLabel":""}},"qOtherTotalSpec":{"qOtherMode":"OTHER_OFF","qOtherCounted":{"qv":"10"},"qOtherLimit":{"qv":"0"},"qOtherLimitMode":"OTHER_GE_LIMIT","qForceBadValueKeeping":true,"qApplyEvenWhenPossiblyWrongResult":true,"qOtherSortMode":"OTHER_SORT_DESCENDING","qTotalMode":"TOTAL_OFF","qReferencedExpression":{}},"qOtherLabel":{"qv":"Others"},"qTotalLabel":{},"qCalcCond":{},"qAttributeExpressions":[],"qAttributeDimensions":[],"qCalcCondition":{"qCond":{},"qMsg":{}}}],"qMeasures":[{"qDef":{"qLabel":"Latest Activity","qTags":[],"qGrouping":"N","qDef":"Max([Sheet Latest Activity Date])","qNumFormat":{"qType":"D","qnDec":2,"qUseThou":0,"qFmt":"YYYY-MM-DD"},"qAggrFunc":"Expr","qAccumulate":0,"qActiveExpression":0,"qExpressions":[],"autoSort":true,"cId":"YCmj","numFormatFromTemplate":true,"textAlign":{"auto":true,"align":"left"},"isCustomFormatted":false},"qSortBy":{"qSortByNumeric":-1,"qSortByLoadOrder":1,"qExpression":{}},"qAttributeExpressions":[],"qAttributeDimensions":[],"qCalcCond":{},"qCalcCondition":{"qCond":{},"qMsg":{}},"qTrendLines":[],"qMiniChartDef":{"qSortBy":{"qExpression":{}},"qOtherTotalSpec":{"qOtherMode":"OTHER_OFF","qOtherCounted":{},"qOtherLimit":{},"qOtherLimitMode":"OTHER_GT_LIMIT","qForceBadValueKeeping":true,"qApplyEvenWhenPossiblyWrongResult":true,"qOtherSortMode":"OTHER_SORT_DESCENDING","qTotalMode":"TOTAL_OFF","qReferencedExpression":{}},"qMaxNumberPoints":-1,"qAttributeExpressions":[]}},{"qLibraryId":"mvyYWMN","qDef":{"qTags":[],"qGrouping":"N","qNumFormat":{"qType":"U","qnDec":10,"qUseThou":0},"qAggrFunc":"Expr","qAccumulate":0,"qActiveExpression":0,"qExpressions":[],"autoSort":true,"cId":"rFpzJY","numFormatFromTemplate":true,"textAlign":{"auto":true,"align":"left"}},"qSortBy":{"qSortByNumeric":-1,"qSortByLoadOrder":1,"qExpression":{}},"qAttributeExpressions":[{"qExpression":"$(c_red_0_green_alpha([Users Accessing Sheet]*10))","qAttribute":true,"id":"cellBackgroundColor"}],"qAttributeDimensions":[],"qCalcCond":{},"qCalcCondition":{"qCond":{},"qMsg":{}},"qTrendLines":[],"qMiniChartDef":{"qSortBy":{"qExpression":{}},"qOtherTotalSpec":{"qOtherMode":"OTHER_OFF","qOtherCounted":{},"qOtherLimit":{},"qOtherLimitMode":"OTHER_GT_LIMIT","qForceBadValueKeeping":true,"qApplyEvenWhenPossiblyWrongResult":true,"qOtherSortMode":"OTHER_SORT_DESCENDING","qTotalMode":"TOTAL_OFF","qReferencedExpression":{}},"qMaxNumberPoints":-1,"qAttributeExpressions":[]}}],"qInterColumnSortOrder":[0,1,2,3,4,8,6,5,7],"qSuppressMissing":true,"qInitialDataFetch":[],"qReductionMode":"N","qMode":"S","qPseudoDimPos":-1,"qNoOfLeftDims":-1,"qMaxStackedCells":5000,"qCalcCond":{},"qTitle":{},"qCalcCondition":{"qCond":{},"qMsg":{}},"qColumnOrder":[0,1,2,3,4,7,5,8,6],"qExpansionState":[],"qDynamicScript":[],"columnOrder":[0,1,2,3,4,7,5,8,6],"columnWidths":[-1,-1,-1,-1,-1,-1,-1,-1,-1],"qLayoutExclude":{"qHyperCubeDef":{"qDimensions":[],"qMeasures":[],"qInterColumnSortOrder":[],"qInitialDataFetch":[],"qReductionMode":"N","qMode":"S","qPseudoDimPos":-1,"qNoOfLeftDims":-1,"qMaxStackedCells":5000,"qCalcCond":{},"qTitle":{},"qCalcCondition":{"qCond":{},"qMsg":{}},"qColumnOrder":[],"qExpansionState":[],"qDynamicScript":[]}}},"showTitles":true,"title":{"qStringExpression":{"qExpr":"='Sheet Usage (' & num(count({<[App Object Type]={\"sheet\"}>} Distinct AppObjectId),'#,##0') & ' Sheets)'"}},"subtitle":"","footnote":"","showDetails":true,"totals":{"show":false,"position":"noTotals","label":"Totals"},"scrolling":{"keepFirstColumnInView":false,"horizontal":true},"multiline":{"wrapTextInHeaders":true,"wrapTextInCells":true},"visualization":"table"},"qChildren":[]},{"qProperty":{"qInfo":{"qId":"tDqdKeP","qType":"table"},"qMetaDef":{},"qHyperCubeDef":{"qDimensions":[{"qLibraryId":"DXqMQM","qDef":{"qGrouping":"N","qFieldDefs":[],"qFieldLabels":[],"qSortCriterias":[{"qSortByNumeric":1,"qSortByAscii":1,"qSortByLoadOrder":1,"qExpression":{}}],"qNumberPresentations":[],"qActiveField":0,"autoSort":true,"cId":"QTJwJU","othersLabel":"Others","textAlign":{"auto":true,"align":"left"},"representation":{"type":"text","urlLabel":""}},"qNullSuppression":true,"qOtherTotalSpec":{"qOtherMode":"OTHER_OFF","qOtherCounted":{"qv":"10"},"qOtherLimit":{"qv":"0"},"qOtherLimitMode":"OTHER_GT_LIMIT","qSuppressOther":true,"qForceBadValueKeeping":true,"qApplyEvenWhenPossiblyWrongResult":true,"qOtherSortMode":"OTHER_SORT_DESCENDING","qTotalMode":"TOTAL_OFF","qReferencedExpression":{}},"qOtherLabel":{"qv":"Others"},"qTotalLabel":{},"qCalcCond":{},"qAttributeExpressions":[],"qAttributeDimensions":[],"qCalcCondition":{"qCond":{},"qMsg":{}}},{"qLibraryId":"pwkJgCV","qDef":{"qGrouping":"N","qFieldDefs":[],"qFieldLabels":[],"qSortCriterias":[{"qSortByNumeric":1,"qSortByAscii":1,"qSortByLoadOrder":1,"qExpression":{}}],"qNumberPresentations":[],"qActiveField":0,"autoSort":true,"cId":"ZWTCPPf","othersLabel":"Others","textAlign":{"auto":true,"align":"left"},"representation":{"type":"text","urlLabel":""}},"qNullSuppression":true,"qOtherTotalSpec":{"qOtherMode":"OTHER_OFF","qOtherCounted":{"qv":"10"},"qOtherLimit":{"qv":"0"},"qOtherLimitMode":"OTHER_GE_LIMIT","qForceBadValueKeeping":true,"qApplyEvenWhenPossiblyWrongResult":true,"qOtherSortMode":"OTHER_SORT_DESCENDING","qTotalMode":"TOTAL_OFF","qReferencedExpression":{}},"qOtherLabel":{"qv":"Others"},"qTotalLabel":{},"qCalcCond":{},"qAttributeExpressions":[],"qAttributeDimensions":[],"qCalcCondition":{"qCond":{},"qMsg":{}}},{"qDef":{"qGrouping":"N","qFieldDefs":["App Created Date"],"qFieldLabels":["App Created"],"qSortCriterias":[{"qSortByNumeric":1,"qSortByAscii":1,"qSortByLoadOrder":1,"qExpression":{}}],"qNumberPresentations":[],"qActiveField":0,"autoSort":true,"cId":"AQXJy","othersLabel":"Others","textAlign":{"auto":true,"align":"left"},"representation":{"type":"text","urlLabel":""}},"qNullSuppression":true,"qOtherTotalSpec":{"qOtherMode":"OTHER_OFF","qOtherCounted":{"qv":"10"},"qOtherLimit":{"qv":"0"},"qOtherLimitMode":"OTHER_GE_LIMIT","qForceBadValueKeeping":true,"qApplyEvenWhenPossiblyWrongResult":true,"qOtherSortMode":"OTHER_SORT_DESCENDING","qTotalMode":"TOTAL_OFF","qReferencedExpression":{}},"qOtherLabel":{"qv":"Others"},"qTotalLabel":{},"qCalcCond":{},"qAttributeExpressions":[],"qAttributeDimensions":[],"qCalcCondition":{"qCond":{},"qMsg":{}}},{"qLibraryId":"PzSvad","qDef":{"qGrouping":"N","qFieldDefs":[],"qFieldLabels":[],"qSortCriterias":[{"qSortByNumeric":1,"qSortByAscii":1,"qSortByLoadOrder":1,"qExpression":{}}],"qNumberPresentations":[],"qActiveField":0,"autoSort":true,"cId":"FrJg","othersLabel":"Others","textAlign":{"auto":true,"align":"left"},"representation":{"type":"text","urlLabel":""}},"qNullSuppression":true,"qOtherTotalSpec":{"qOtherMode":"OTHER_ABS_LIMITED","qOtherCounted":{"qv":"10"},"qOtherLimit":{"qv":"0"},"qOtherLimitMode":"OTHER_GT_LIMIT","qSuppressOther":true,"qForceBadValueKeeping":true,"qApplyEvenWhenPossiblyWrongResult":true,"qOtherSortMode":"OTHER_SORT_DESCENDING","qTotalMode":"TOTAL_OFF","qReferencedExpression":{}},"qOtherLabel":{"qv":"Others"},"qTotalLabel":{},"qCalcCond":{},"qAttributeExpressions":[],"qAttributeDimensions":[],"qCalcCondition":{"qCond":{},"qMsg":{}}}],"qMeasures":[{"qLibraryId":"LyLgJt","qDef":{"qTags":[],"qGrouping":"N","qNumFormat":{"qType":"U","qnDec":10,"qUseThou":0},"qAggrFunc":"Expr","qAccumulate":0,"qActiveExpression":0,"qExpressions":[],"autoSort":true,"cId":"JDdPm","numFormatFromTemplate":true,"textAlign":{"auto":true,"align":"left"}},"qSortBy":{"qSortByNumeric":-1,"qSortByLoadOrder":1,"qExpression":{}},"qAttributeExpressions":[],"qAttributeDimensions":[],"qCalcCond":{},"qCalcCondition":{"qCond":{},"qMsg":{}},"qTrendLines":[],"qMiniChartDef":{"qSortBy":{"qExpression":{}},"qOtherTotalSpec":{"qOtherMode":"OTHER_OFF","qOtherCounted":{},"qOtherLimit":{},"qOtherLimitMode":"OTHER_GT_LIMIT","qForceBadValueKeeping":true,"qApplyEvenWhenPossiblyWrongResult":true,"qOtherSortMode":"OTHER_SORT_DESCENDING","qTotalMode":"TOTAL_OFF","qReferencedExpression":{}},"qMaxNumberPoints":-1,"qAttributeExpressions":[]}},{"qLibraryId":"ujSJU","qDef":{"qTags":[],"qGrouping":"N","qNumFormat":{"qType":"U","qnDec":10,"qUseThou":0},"qAggrFunc":"Expr","qAccumulate":0,"qActiveExpression":0,"qExpressions":[],"autoSort":true,"cId":"PWcGXQn","numFormatFromTemplate":true,"textAlign":{"auto":true,"align":"left"}},"qSortBy":{"qSortByNumeric":-1,"qSortByLoadOrder":1,"qExpression":{}},"qAttributeExpressions":[],"qAttributeDimensions":[],"qCalcCond":{},"qCalcCondition":{"qCond":{},"qMsg":{}},"qTrendLines":[],"qMiniChartDef":{"qSortBy":{"qExpression":{}},"qOtherTotalSpec":{"qOtherMode":"OTHER_OFF","qOtherCounted":{},"qOtherLimit":{},"qOtherLimitMode":"OTHER_GT_LIMIT","qForceBadValueKeeping":true,"qApplyEvenWhenPossiblyWrongResult":true,"qOtherSortMode":"OTHER_SORT_DESCENDING","qTotalMode":"TOTAL_OFF","qReferencedExpression":{}},"qMaxNumberPoints":-1,"qAttributeExpressions":[]}},{"qLibraryId":"5846921c-9bce-41cf-8ef7-dd4f3e995186","qDef":{"qTags":[],"qGrouping":"N","qNumFormat":{"qType":"U","qnDec":10,"qUseThou":0},"qAggrFunc":"Expr","qAccumulate":0,"qActiveExpression":0,"qExpressions":[],"autoSort":false,"cId":"pUkXjWp","numFormatFromTemplate":true,"textAlign":{"auto":true,"align":"left"}},"qSortBy":{"qSortByNumeric":-1,"qSortByLoadOrder":1,"qExpression":{}},"qAttributeExpressions":[{"qExpression":"$(c_red_breeze_alpha([Unused Base Sheets $(=[Latest Activity Measure])]*12))","qAttribute":true,"id":"cellBackgroundColor"}],"qAttributeDimensions":[],"qCalcCond":{},"qCalcCondition":{"qCond":{},"qMsg":{}},"qTrendLines":[],"qMiniChartDef":{"qSortBy":{"qExpression":{}},"qOtherTotalSpec":{"qOtherMode":"OTHER_OFF","qOtherCounted":{},"qOtherLimit":{},"qOtherLimitMode":"OTHER_GT_LIMIT","qForceBadValueKeeping":true,"qApplyEvenWhenPossiblyWrongResult":true,"qOtherSortMode":"OTHER_SORT_DESCENDING","qTotalMode":"TOTAL_OFF","qReferencedExpression":{}},"qMaxNumberPoints":-1,"qAttributeExpressions":[]}},{"qLibraryId":"27ef5c71-d15b-45f9-bbf1-5784783d8ec1","qDef":{"qTags":[],"qGrouping":"N","qNumFormat":{"qType":"U","qnDec":10,"qUseThou":0},"qAggrFunc":"Expr","qAccumulate":0,"qActiveExpression":0,"qExpressions":[],"autoSort":true,"cId":"TfUf","numFormatFromTemplate":true,"textAlign":{"auto":true,"align":"left"}},"qSortBy":{"qSortByNumeric":-1,"qSortByLoadOrder":1,"qExpression":{}},"qAttributeExpressions":[],"qAttributeDimensions":[],"qCalcCond":{},"qCalcCondition":{"qCond":{},"qMsg":{}},"qTrendLines":[],"qMiniChartDef":{"qSortBy":{"qExpression":{}},"qOtherTotalSpec":{"qOtherMode":"OTHER_OFF","qOtherCounted":{},"qOtherLimit":{},"qOtherLimitMode":"OTHER_GT_LIMIT","qForceBadValueKeeping":true,"qApplyEvenWhenPossiblyWrongResult":true,"qOtherSortMode":"OTHER_SORT_DESCENDING","qTotalMode":"TOTAL_OFF","qReferencedExpression":{}},"qMaxNumberPoints":-1,"qAttributeExpressions":[]}},{"qLibraryId":"124a6ce5-ea34-41a8-ab4c-e1a5167caaef","qDef":{"qTags":[],"qGrouping":"N","qNumFormat":{"qType":"U","qnDec":10,"qUseThou":0},"qAggrFunc":"Expr","qAccumulate":0,"qActiveExpression":0,"qExpressions":[],"autoSort":false,"cId":"EdHLDX","numFormatFromTemplate":true,"textAlign":{"auto":true,"align":"left"}},"qSortBy":{"qSortByNumeric":-1,"qSortByLoadOrder":1,"qExpression":{}},"qAttributeExpressions":[{"qExpression":"$(c_orange_breeze_alpha([Unused Community Sheets $(=[Latest Activity Measure])]*12))","qAttribute":true,"id":"cellBackgroundColor"}],"qAttributeDimensions":[],"qCalcCond":{},"qCalcCondition":{"qCond":{},"qMsg":{}},"qTrendLines":[],"qMiniChartDef":{"qSortBy":{"qExpression":{}},"qOtherTotalSpec":{"qOtherMode":"OTHER_OFF","qOtherCounted":{},"qOtherLimit":{},"qOtherLimitMode":"OTHER_GT_LIMIT","qForceBadValueKeeping":true,"qApplyEvenWhenPossiblyWrongResult":true,"qOtherSortMode":"OTHER_SORT_DESCENDING","qTotalMode":"TOTAL_OFF","qReferencedExpression":{}},"qMaxNumberPoints":-1,"qAttributeExpressions":[]}},{"qLibraryId":"664a255f-5fc5-408c-9900-45b8aa4f038c","qDef":{"qTags":[],"qGrouping":"N","qNumFormat":{"qType":"U","qnDec":10,"qUseThou":0},"qAggrFunc":"Expr","qAccumulate":0,"qActiveExpression":0,"qExpressions":[],"autoSort":true,"cId":"PLmcW","numFormatFromTemplate":true,"textAlign":{"auto":true,"align":"left"}},"qSortBy":{"qSortByNumeric":-1,"qSortByLoadOrder":1,"qExpression":{}},"qAttributeExpressions":[],"qAttributeDimensions":[],"qCalcCond":{},"qCalcCondition":{"qCond":{},"qMsg":{}},"qTrendLines":[],"qMiniChartDef":{"qSortBy":{"qExpression":{}},"qOtherTotalSpec":{"qOtherMode":"OTHER_OFF","qOtherCounted":{},"qOtherLimit":{},"qOtherLimitMode":"OTHER_GT_LIMIT","qForceBadValueKeeping":true,"qApplyEvenWhenPossiblyWrongResult":true,"qOtherSortMode":"OTHER_SORT_DESCENDING","qTotalMode":"TOTAL_OFF","qReferencedExpression":{}},"qMaxNumberPoints":-1,"qAttributeExpressions":[]}},{"qLibraryId":"d5300069-6bc8-492a-8b47-84373aba2963","qDef":{"qTags":[],"qGrouping":"N","qNumFormat":{"qType":"U","qnDec":10,"qUseThou":0},"qAggrFunc":"Expr","qAccumulate":0,"qActiveExpression":0,"qExpressions":[],"autoSort":true,"cId":"aWAkaj","numFormatFromTemplate":true,"textAlign":{"auto":true,"align":"left"}},"qSortBy":{"qSortByNumeric":-1,"qSortByLoadOrder":1,"qExpression":{}},"qAttributeExpressions":[{"qExpression":"$(c_teal_breeze_alpha([Unused Private Sheets $(=[Latest Activity Measure])]*12))","qAttribute":true,"id":"cellBackgroundColor"}],"qAttributeDimensions":[],"qCalcCond":{},"qCalcCondition":{"qCond":{},"qMsg":{}},"qTrendLines":[],"qMiniChartDef":{"qSortBy":{"qExpression":{}},"qOtherTotalSpec":{"qOtherMode":"OTHER_OFF","qOtherCounted":{},"qOtherLimit":{},"qOtherLimitMode":"OTHER_GT_LIMIT","qForceBadValueKeeping":true,"qApplyEvenWhenPossiblyWrongResult":true,"qOtherSortMode":"OTHER_SORT_DESCENDING","qTotalMode":"TOTAL_OFF","qReferencedExpression":{}},"qMaxNumberPoints":-1,"qAttributeExpressions":[]}},{"qLibraryId":"mvyYWMN","qDef":{"qTags":[],"qGrouping":"N","qNumFormat":{"qType":"U","qnDec":10,"qUseThou":0},"qAggrFunc":"Expr","qAccumulate":0,"qActiveExpression":0,"qExpressions":[],"autoSort":true,"cId":"hpqCKP","numFormatFromTemplate":true,"textAlign":{"auto":true,"align":"left"}},"qSortBy":{"qSortByNumeric":-1,"qSortByLoadOrder":1,"qExpression":{}},"qAttributeExpressions":[{"qExpression":"$(c_red_0_green_alpha([Users Accessing Sheet]*10))","qAttribute":true,"id":"cellBackgroundColor"}],"qAttributeDimensions":[],"qCalcCond":{},"qCalcCondition":{"qCond":{},"qMsg":{}},"qTrendLines":[],"qMiniChartDef":{"qSortBy":{"qExpression":{}},"qOtherTotalSpec":{"qOtherMode":"OTHER_OFF","qOtherCounted":{},"qOtherLimit":{},"qOtherLimitMode":"OTHER_GT_LIMIT","qForceBadValueKeeping":true,"qApplyEvenWhenPossiblyWrongResult":true,"qOtherSortMode":"OTHER_SORT_DESCENDING","qTotalMode":"TOTAL_OFF","qReferencedExpression":{}},"qMaxNumberPoints":-1,"qAttributeExpressions":[]}},{"qLibraryId":"fapFVs","qDef":{"qTags":[],"qGrouping":"N","qNumFormat":{"qType":"U","qnDec":10,"qUseThou":0},"qAggrFunc":"Expr","qAccumulate":0,"qActiveExpression":0,"qExpressions":[],"autoSort":true,"cId":"CKjVq","numFormatFromTemplate":true,"textAlign":{"auto":true,"align":"left"}},"qSortBy":{"qSortByNumeric":-1,"qSortByLoadOrder":1,"qExpression":{}},"qAttributeExpressions":[],"qAttributeDimensions":[],"qCalcCond":{},"qCalcCondition":{"qCond":{},"qMsg":{}},"qTrendLines":[],"qMiniChartDef":{"qSortBy":{"qExpression":{}},"qOtherTotalSpec":{"qOtherMode":"OTHER_OFF","qOtherCounted":{},"qOtherLimit":{},"qOtherLimitMode":"OTHER_GT_LIMIT","qForceBadValueKeeping":true,"qApplyEvenWhenPossiblyWrongResult":true,"qOtherSortMode":"OTHER_SORT_DESCENDING","qTotalMode":"TOTAL_OFF","qReferencedExpression":{}},"qMaxNumberPoints":-1,"qAttributeExpressions":[]}}],"qInterColumnSortOrder":[6,8,0,1,11,4,5,7,9,3,12,2,10],"qSuppressMissing":true,"qInitialDataFetch":[],"qReductionMode":"N","qMode":"S","qPseudoDimPos":-1,"qNoOfLeftDims":-1,"qMaxStackedCells":5000,"qCalcCond":{},"qTitle":{},"qCalcCondition":{"qCond":{},"qMsg":{}},"qColumnOrder":[0,1,2,4,5,6,7,8,9,10,11,12,3],"qExpansionState":[],"qDynamicScript":[],"columnOrder":[0,1,2,4,5,6,7,8,9,10,11,12,3],"columnWidths":[-1,-1,-1,-1,-1,-1,-1,-1,-1,-1,-1,-1,-1],"qLayoutExclude":{"qHyperCubeDef":{"qDimensions":[],"qMeasures":[],"qInterColumnSortOrder":[],"qInitialDataFetch":[],"qReductionMode":"N","qMode":"S","qPseudoDimPos":-1,"qNoOfLeftDims":-1,"qMaxStackedCells":5000,"qCalcCond":{},"qTitle":{},"qCalcCondition":{"qCond":{},"qMsg":{}},"qColumnOrder":[],"qExpansionState":[],"qDynamicScript":[]}}},"showTitles":true,"title":{"qStringExpression":{"qExpr":"='App > Sheet Usage Summary  (' & num(count({<[App Object Type]={\"sheet\"}>} Distinct AppId),'#,##0') & ' Apps with Sheets)'"}},"subtitle":"","footnote":"","showDetails":true,"totals":{"show":true,"position":"noTotals","label":"Totals"},"scrolling":{"keepFirstColumnInView":false,"horizontal":true},"multiline":{"wrapTextInHeaders":true,"wrapTextInCells":true},"visualization":"table"},"qChildren":[]},{"qProperty":{"qInfo":{"qId":"UCgsfS","qType":"barchart"},"qMetaDef":{},"qHyperCubeDef":{"qDimensions":[{"qDef":{"qGrouping":"N","qFieldDefs":["=[App Name] & ' ' & AppId"],"qFieldLabels":["App"],"qSortCriterias":[{"qSortByAscii":1,"qSortByLoadOrder":1,"qSortByExpression":-1,"qExpression":{"qv":"=Count({<[App Object Type]={\"sheet\"}>} Distinct AppObjectId)"}}],"qNumberPresentations":[],"qActiveField":0,"autoSort":false,"cId":"QTJwJU","othersLabel":"Others","textAlign":{"auto":true,"align":"left"},"representation":{"type":"text","urlLabel":""}},"qNullSuppression":true,"qOtherTotalSpec":{"qOtherMode":"OTHER_OFF","qOtherCounted":{"qv":"10"},"qOtherLimit":{"qv":"0"},"qOtherLimitMode":"OTHER_GE_LIMIT","qForceBadValueKeeping":true,"qApplyEvenWhenPossiblyWrongResult":true,"qOtherSortMode":"OTHER_SORT_DESCENDING","qTotalMode":"TOTAL_OFF","qReferencedExpression":{}},"qOtherLabel":{"qv":"Others"},"qTotalLabel":{},"qCalcCond":{},"qAttributeExpressions":[],"qAttributeDimensions":[],"qCalcCondition":{"qCond":{},"qMsg":{}},"title":"App","othersLabel":"Others"}],"qMeasures":[{"qLibraryId":"ujSJU","qDef":{"qTags":[],"qGrouping":"N","qNumFormat":{"qType":"U","qnDec":10,"qUseThou":0},"qAggrFunc":"Expr","qAccumulate":0,"qActiveExpression":0,"qExpressions":[],"autoSort":true,"cId":"PWcGXQn","numFormatFromTemplate":true,"textAlign":{"auto":true,"align":"left"}},"qSortBy":{"qSortByNumeric":-1,"qSortByLoadOrder":1,"qExpression":{}},"qAttributeExpressions":[],"qAttributeDimensions":[],"qCalcCond":{},"qCalcCondition":{"qCond":{},"qMsg":{}},"qTrendLines":[],"qMiniChartDef":{"qSortBy":{"qExpression":{}},"qOtherTotalSpec":{"qOtherMode":"OTHER_OFF","qOtherCounted":{},"qOtherLimit":{},"qOtherLimitMode":"OTHER_GT_LIMIT","qForceBadValueKeeping":true,"qApplyEvenWhenPossiblyWrongResult":true,"qOtherSortMode":"OTHER_SORT_DESCENDING","qTotalMode":"TOTAL_OFF","qReferencedExpression":{}},"qMaxNumberPoints":-1,"qAttributeExpressions":[]},"title":"Base Sheets"},{"qLibraryId":"27ef5c71-d15b-45f9-bbf1-5784783d8ec1","qDef":{"qTags":[],"qGrouping":"N","qNumFormat":{"qType":"U","qnDec":10,"qUseThou":0},"qAggrFunc":"Expr","qAccumulate":0,"qActiveExpression":0,"qExpressions":[],"autoSort":true,"cId":"TfUf","numFormatFromTemplate":true,"textAlign":{"auto":true,"align":"left"}},"qSortBy":{"qSortByNumeric":-1,"qSortByLoadOrder":1,"qExpression":{}},"qAttributeExpressions":[],"qAttributeDimensions":[],"qCalcCond":{},"qCalcCondition":{"qCond":{},"qMsg":{}},"qTrendLines":[],"qMiniChartDef":{"qSortBy":{"qExpression":{}},"qOtherTotalSpec":{"qOtherMode":"OTHER_OFF","qOtherCounted":{},"qOtherLimit":{},"qOtherLimitMode":"OTHER_GT_LIMIT","qForceBadValueKeeping":true,"qApplyEvenWhenPossiblyWrongResult":true,"qOtherSortMode":"OTHER_SORT_DESCENDING","qTotalMode":"TOTAL_OFF","qReferencedExpression":{}},"qMaxNumberPoints":-1,"qAttributeExpressions":[]},"title":"Community Sheets"},{"qLibraryId":"664a255f-5fc5-408c-9900-45b8aa4f038c","qDef":{"qTags":[],"qGrouping":"N","qNumFormat":{"qType":"U","qnDec":10,"qUseThou":0},"qAggrFunc":"Expr","qAccumulate":0,"qActiveExpression":0,"qExpressions":[],"autoSort":true,"cId":"PLmcW","numFormatFromTemplate":true,"textAlign":{"auto":true,"align":"left"}},"qSortBy":{"qSortByNumeric":-1,"qSortByLoadOrder":1,"qExpression":{}},"qAttributeExpressions":[],"qAttributeDimensions":[],"qCalcCond":{},"qCalcCondition":{"qCond":{},"qMsg":{}},"qTrendLines":[],"qMiniChartDef":{"qSortBy":{"qExpression":{}},"qOtherTotalSpec":{"qOtherMode":"OTHER_OFF","qOtherCounted":{},"qOtherLimit":{},"qOtherLimitMode":"OTHER_GT_LIMIT","qForceBadValueKeeping":true,"qApplyEvenWhenPossiblyWrongResult":true,"qOtherSortMode":"OTHER_SORT_DESCENDING","qTotalMode":"TOTAL_OFF","qReferencedExpression":{}},"qMaxNumberPoints":-1,"qAttributeExpressions":[]},"title":"Private Sheets"}],"qInterColumnSortOrder":[0,1,2,3],"qSuppressMissing":true,"qInitialDataFetch":[{"qLeft":0,"qTop":0,"qWidth":17,"qHeight":500}],"qReductionMode":"N","qMode":"S","qPseudoDimPos":-1,"qNoOfLeftDims":-1,"qAlwaysFullyExpanded":true,"qMaxStackedCells":5000,"qCalcCond":{},"qTitle":{},"qCalcCondition":{"qCond":{},"qMsg":{}},"qColumnOrder":[0,2,3,4,1],"qExpansionState":[],"qDynamicScript":[],"columnOrder":[0,2,3,4,1],"columnWidths":[-1,-1,-1,-1,-1],"qLayoutExclude":{"qHyperCubeDef":{"qDimensions":[],"qMeasures":[],"qInterColumnSortOrder":[0,2,3,4,1],"qInitialDataFetch":[],"qReductionMode":"N","qMode":"S","qPseudoDimPos":-1,"qNoOfLeftDims":-1,"qMaxStackedCells":5000,"qCalcCond":{},"qTitle":{},"qCalcCondition":{"qCond":{},"qMsg":{}},"qColumnOrder":[],"qExpansionState":[],"qDynamicScript":[]}}},"refLine":{"refLines":[]},"showTitles":true,"title":{"qStringExpression":{"qExpr":"'App Sheet Summary'"}},"subtitle":"","footnote":"","showDetails":true,"barGrouping":{"grouping":"stacked"},"orientation":"horizontal","scrollStartPos":0,"gridLine":{"auto":true,"spacing":2},"dataPoint":{"showLabels":true},"color":{"auto":true,"mode":"byExpression","useBaseColors":"off","paletteColor":{"index":12},"useDimColVal":true,"useMeasureGradient":true,"persistent":true,"expressionIsColor":true,"expressionLabel":"","measureScheme":"sg","reverseScheme":false,"dimensionScheme":"12","autoMinMax":true,"measureMin":0,"measureMax":10,"altLabel":"ujSJU","byMeasureDef":{"label":"ujSJU","key":"ujSJU","type":"libraryItem"}},"legend":{"show":true,"dock":"top","showTitle":false},"dimensionAxis":{"continuousAuto":true,"show":"labels","label":"auto","dock":"near"},"preferContinuousAxis":true,"showMiniChartForContinuousAxis":true,"measureAxis":{"show":"labels","dock":"near","spacing":1,"autoMinMax":true,"minMax":"min","min":0,"max":10},"visualization":"barchart","qLayoutExclude":{}},"qChildren":[]}]}}}